Metadata-Version: 2.1
Name: MCfun
Version: 0.2.5
Summary: A library to calculate multi-collinear functionl
Home-page: https://github.com/Multi-collinear/MCfun
License-File: LICENSE
